qsi_pulse_reader/__init__.py
qsi_pulse_reader/qsi_pulse_reader.cp311-win_amd64.pyd
qsi_pulse_reader-1.1.2.dist-info/licenses/LICENSE.rst
qsi_pulse_reader-1.1.2.dist-info/METADATA
qsi_pulse_reader-1.1.2.dist-info/WHEEL
qsi_pulse_reader-1.1.2.dist-info/top_level.txt
qsi_pulse_reader-1.1.2.dist-info/RECORD
