Metadata-Version: 2.4
Name: qsi-pulse-reader
Version: 1.1.2
Summary: Library for reading pulses.bin files
Author-email: Eric Hermes <community@quantum-si.com>
Maintainer-email: Eric Hermes <community@quantum-si.com>
License-Expression: LicenseRef-Quantum-Si-Software-License-Agreement
Project-URL: Homepage, https://www.quantum-si.com/
Project-URL: Repository, https://github.com/QuantumSi/qsi-pulse-reader
Project-URL: Bug Tracker, https://github.com/QuantumSi/qsi-pulse-reader/issues
Requires-Python: <=3.14,>=3.10
License-File: LICENSE.rst
Requires-Dist: numpy>=1.16.0
Requires-Dist: pandas<3.0.0,>=1.5.3
Provides-Extra: test
Requires-Dist: pytest>=7.4.0; extra == "test"
Dynamic: license-file
